<?xml version="1.0" encoding="UTF-8" standalone="no"?>
<profil xmlns="http://myGame/tux" xmlns:xsi="http://www.w3.org/2001/XMLSchema-instance" xsi:schemaLocation="http://myGame/tux ../xsd/profil.xsd">
    <nom>Lea</nom>
    <avatar>conan.jpg</avatar>
    <anniversaire>2023-02-12</anniversaire>
    <parties>
        <partie date="2023-02-12" trouvé="100">
            <temps>4</temps>
            <mot niveau="1">grue</mot>
        </partie>
        <partie date="2023-02-12" trouvé="100">
            <temps>14</temps>
            <mot niveau="4">absolument</mot>
        </partie>
    </parties>
</profil>